{
  "header": {
    "version": 4,
    "description": "Karaoke Mugen Karaoke Data File"
  },
  "medias": [
    {
      "default": true,
      "duration": 284,
      "filename": "007ba509-46e5-410a-9753-e8aa389700f0.webm",
      "filesize": 11066166,
      "loudnorm": "-15.44,-1.94,7.60,-25.82,-0.38",
      "lyrics": [
        {
          "default": true,
          "filename": "007ba509-46e5-410a-9753-e8aa389700f0.ass",
          "version": "Default"
        }
      ],
      "version": "Default"
    }
  ],
  "data": {
    "created_at": "2025-02-10T18:43:24.672Z",
    "ignoreHooks": false,
    "kid": "007ba509-46e5-410a-9753-e8aa389700f0",
    "modified_at": "2025-02-10T18:43:24.824Z",
    "repository": "kara.moe",
    "songname": "JPN - Rip Slyme - MV - Rakuen Baby",
    "tags": {
      "authors": [
        "6ff07670-8a91-4988-bcf3-e844b802928c"
      ],
      "collections": [
        "dbcf2c22-524d-4708-99bb-601703633927"
      ],
      "families": [
        "5391f9fe-638c-415f-8dc9-958e3a2c5787"
      ],
      "langs": [
        "4dcf9614-7914-42aa-99f4-dbce2e059133"
      ],
      "misc": [
        "1d6ceadf-a885-47e5-b23b-c07bf668a424"
      ],
      "singergroups": [
        "58132eea-66d3-49dc-b952-496f2fe13f7f"
      ],
      "songtypes": [
        "7be1b15c-cff8-4b37-a649-5c90f3d569a9"
      ],
      "groups": [
        "3c14c864-533c-49e6-a3cc-6969f1233775"
      ]
    },
    "titles": {
      "qro": "Rakuen Baby",
      "jpn": "楽園ベイベー"
    },
    "titles_default_language": "qro",
    "year": 2002
  }
}