{
  "header": {
    "version": 4,
    "description": "Karaoke Mugen Karaoke Data File"
  },
  "medias": [
    {
      "version": "Default",
      "filename": "ENG - Kaze no Tani no Nausicaa - MOVIE AMV - If Everyone Cared.mp4",
      "loudnorm": "-7.46,0.79,8.30,-17.71,-1.47",
      "filesize": 29037592,
      "duration": 218,
      "default": true,
      "lyrics": [
        {
          "filename": "ENG - Kaze no Tani no Nausicaa - MOVIE AMV - If Everyone Cared.ass",
          "default": true,
          "version": "Default"
        }
      ]
    }
  ],
  "data": {
    "created_at": "2019-06-08T20:38:38.000Z",
    "ignoreHooks": false,
    "kid": "cdb8c382-77f5-4b38-a210-f1d7bb5caedc",
    "modified_at": "2024-07-08T21:08:52.265Z",
    "repository": "kara.moe",
    "tags": {
      "authors": [
        "88321964-7c14-4305-85c1-0f4941aadfde"
      ],
      "collections": [
        "c7db86a0-ff64-4044-9be4-66dd1ef1d1c1"
      ],
      "creators": [
        "46cc6a97-4290-48b1-b4ff-5f60359674ef"
      ],
      "families": [
        "0377db02-3af6-43b8-9b08-c759df3d25c3"
      ],
      "groups": [
        "2b4e9972-5e17-481b-99f5-d0787c0ada56",
        "3c14c864-533c-49e6-a3cc-6969f1233775"
      ],
      "langs": [
        "de5eda1c-5fb3-46a6-9606-d4554fc5a1d6"
      ],
      "origins": [
        "c8ca9dea-d8b4-48fe-8427-d911653232e9"
      ],
      "series": [
        "1a0c67e7-2ad5-49fc-9283-fbfcaf522af9"
      ],
      "singergroups": [
        "0d246dc1-54c6-4adc-87a9-b67d8e06b1e0"
      ],
      "songtypes": [
        "a6c79ce5-89ee-4d50-afe8-3abd7317f6c2"
      ],
      "songwriters": [
        "0d246dc1-54c6-4adc-87a9-b67d8e06b1e0"
      ]
    },
    "titles": {
      "eng": "If Everyone Cared"
    },
    "titles_default_language": "eng",
    "year": 2006
  }
}