{
  "header": {
    "version": 4,
    "description": "Karaoke Mugen Karaoke Data File"
  },
  "medias": [
    {
      "version": "Default",
      "filename": "ENG - Ginga Eiyuu Densetsu - OVA OP1 - Skies of Love.mp4",
      "audiogain": 5.2,
      "filesize": 34519729,
      "duration": 92,
      "default": true,
      "lyrics": [
        {
          "filename": "ENG - Ginga Eiyuu Densetsu - OVA OP1 - Skies of Love.ass",
          "default": true,
          "version": "Default",
          "subchecksum": "ac4870aba079f2c0db1097dd513c6975"
        }
      ]
    }
  ],
  "data": {
    "created_at": "Wed Oct 11 2017 19:02:33 GMT+0200 (GMT+02:00)",
    "kid": "49484267-1c2f-4555-8b4a-bd88fd30ee16",
    "modified_at": "Sat Oct 13 2018 00:24:16 GMT+0200 (GMT+02:00)",
    "repository": "kara.moe",
    "sids": [
      "6656c553-99e5-45c2-a013-74406bdf7364"
    ],
    "songorder": 1,
    "tags": {
      "authors": [
        "56ee67d5-8706-4b61-9f4c-9d99e9cf80e8"
      ],
      "creators": [
        "b07ed549-7bfb-4dbd-8271-671eb632ba15",
        "a590547a-0ccc-4ec7-953d-59c9ee48df87",
        "c2984f8d-dfe2-4a89-84f4-857acdcbf329"
      ],
      "families": [
        "0377db02-3af6-43b8-9b08-c759df3d25c3"
      ],
      "groups": [
        "7792cc27-9ff9-4d47-9287-2338b7db1575"
      ],
      "langs": [
        "de5eda1c-5fb3-46a6-9606-d4554fc5a1d6"
      ],
      "origins": [
        "2a6ef087-a000-4f8e-aeb5-9a7968756a36"
      ],
      "singers": [
        "03b69ce8-c0fd-4c4b-a9f0-ff2e7c7e496c"
      ],
      "songtypes": [
        "f02ad9b3-0bd9-4aad-85b3-9976739ba0e4"
      ],
      "songwriters": [
        "03b69ce8-c0fd-4c4b-a9f0-ff2e7c7e496c"
      ]
    },
    "title": "Skies of Love",
    "year": 1988
  }
}