{
  "header": {
    "version": 4,
    "description": "Karaoke Mugen Karaoke Data File"
  },
  "medias": [
    {
      "version": "Default",
      "filename": "ENG - beatmania IIDX - GAME IN - Apocalypse ~dirge of swans~.mp4",
      "audiogain": 3.81,
      "filesize": 43794162,
      "duration": 137,
      "default": true,
      "lyrics": [
        {
          "filename": "ENG - beatmania IIDX - GAME IN - Apocalypse ~dirge of swans~.ass",
          "default": true,
          "version": "Default",
          "subchecksum": "bc123d7e671f24ae3063ed4863a74ac1"
        }
      ]
    }
  ],
  "data": {
    "created_at": "2019-06-08T23:14:06.000Z",
    "kid": "c1e97bd7-631d-4ebe-ad90-dc114b44562f",
    "modified_at": "2019-06-08T23:22:01.000Z",
    "repository": "kara.moe",
    "sids": [
      "b6d2d054-d875-44bc-a5a7-218fca59c358"
    ],
    "tags": {
      "authors": [
        "076236f4-5755-495e-a827-e86edce43e20"
      ],
      "creators": [
        "22092200-b324-4277-8269-b8b0929f42c1"
      ],
      "families": [
        "dbedd6b3-d125-4cd8-aa32-c4175e4ca3a3"
      ],
      "groups": [
        "3c14c864-533c-49e6-a3cc-6969f1233775"
      ],
      "langs": [
        "de5eda1c-5fb3-46a6-9606-d4554fc5a1d6"
      ],
      "singers": [
        "e0054516-88d0-4b76-b94c-cc6d7c5e3e63"
      ],
      "songtypes": [
        "5e5250d9-351a-4a82-98eb-55db50ad8962"
      ],
      "songwriters": [
        "3d37cf90-c62a-4c79-8d08-2156c0ccbd6b"
      ]
    },
    "title": "Apocalypse ~dirge of swans~",
    "year": 2006
  }
}