{
  "header": {
    "version": 4,
    "description": "Karaoke Mugen Karaoke Data File"
  },
  "medias": [
    {
      "version": "Default",
      "filename": "FRE - di13774n73 - AUDIO OT - CSS.mp3",
      "loudnorm": "-13.39,-0.07,5.30,-23.56,-1.45",
      "filesize": 3639688,
      "duration": 148,
      "default": true,
      "lyrics": [
        {
          "filename": "FRE - di13774n73 - AUDIO OT - CSS.ass",
          "default": true,
          "version": "Default"
        }
      ]
    }
  ],
  "data": {
    "created_at": "2024-07-31T20:07:16.259Z",
    "ignoreHooks": false,
    "kid": "020d7668-1e06-4ccb-baa7-2b562b67d104",
    "modified_at": "2024-08-03T14:08:09.049Z",
    "repository": "kara.moe",
    "tags": {
      "authors": [
        "dde9f8ee-c046-42ca-8d1d-4a649bcf9a5d"
      ],
      "collections": [
        "c7db86a0-ff64-4044-9be4-66dd1ef1d1c1"
      ],
      "creators": [
        "111667e5-5c3c-4b9f-b350-dd10c369ae9b"
      ],
      "groups": [
        "3c14c864-533c-49e6-a3cc-6969f1233775"
      ],
      "langs": [
        "fd8072b7-4d9b-45d4-8f5b-a931a830edef"
      ],
      "misc": [
        "cef35a27-3bf0-48c9-beb2-d245ba62ea6b"
      ],
      "singers": [
        "111667e5-5c3c-4b9f-b350-dd10c369ae9b"
      ],
      "songtypes": [
        "42a262ae-acba-4ab5-a446-c5789c96c821",
        "97769615-a2e5-4f36-8c23-b2ce2ce3c460"
      ],
      "songwriters": [
        "111667e5-5c3c-4b9f-b350-dd10c369ae9b"
      ]
    },
    "titles": {
      "fre": "CSS"
    },
    "titles_default_language": "fre",
    "year": 2006
  }
}