{
  "header": {
    "version": 4,
    "description": "Karaoke Mugen Karaoke Data File"
  },
  "medias": [
    {
      "version": "Default",
      "filename": "FRE - Fushigi no Umi no Nadia - MV - Nadia, le secret de l'eau bleue.mp4",
      "audiogain": 0.43,
      "filesize": 17112940,
      "duration": 119,
      "default": true,
      "lyrics": [
        {
          "filename": "FRE - Fushigi no Umi no Nadia - MV - Nadia, le secret de l'eau bleue.ass",
          "default": true,
          "version": "Default",
          "subchecksum": "e219bacb5e16c04221f81654c1b7e10d"
        }
      ]
    }
  ],
  "data": {
    "created_at": "2017-10-11T15:01:53.000Z",
    "kid": "9f354578-15d7-4672-8c26-bdcdebe2cb9c",
    "modified_at": "2019-10-20T11:51:01.000Z",
    "repository": "kara.moe",
    "sids": [
      "658e2c11-22ee-4f44-98d1-60735e156020"
    ],
    "tags": {
      "authors": [
        "5bdaba57-27f8-4568-8806-76a807728766"
      ],
      "creators": [
        "dd729cab-2a78-4282-a402-b242e927a0a5"
      ],
      "families": [
        "0377db02-3af6-43b8-9b08-c759df3d25c3"
      ],
      "groups": [
        "24db50aa-a126-4d34-a48a-e45db79c4245",
        "cebcdc5d-31af-4c83-a744-680885904b73",
        "f5e7d2fc-0cbb-4fb9-a84a-b25dfb0e9e77"
      ],
      "langs": [
        "fd8072b7-4d9b-45d4-8f5b-a931a830edef"
      ],
      "origins": [
        "938de218-5343-4865-94d3-fb33f2eaa152"
      ],
      "singers": [
        "4ab90991-758f-4942-99d3-17355e4698c0"
      ],
      "songtypes": [
        "7be1b15c-cff8-4b37-a649-5c90f3d569a9"
      ]
    },
    "title": "Nadia, le secret de l'eau bleue",
    "year": 1990
  }
}