{
  "header": {
    "version": 4,
    "description": "Karaoke Mugen Karaoke Data File"
  },
  "medias": [
    {
      "version": "Default",
      "filename": "GER - Fushigi no Umi no Nadia - OP - Die Macht des Zaubersteins.mp4",
      "audiogain": -2.07,
      "filesize": 116476053,
      "duration": 91,
      "default": true,
      "lyrics": [
        {
          "filename": "GER - Fushigi no Umi no Nadia - OP - Die Macht des Zaubersteins.ass",
          "default": true,
          "version": "Default",
          "subchecksum": "8ef4fff36f23a173267949d1fb6c0a63"
        }
      ]
    }
  ],
  "data": {
    "created_at": "2019-12-08T13:33:52.529Z",
    "kid": "a1447773-4f56-4bbb-9f74-f8e13cefec27",
    "modified_at": "2019-12-08T13:33:57.288Z",
    "repository": "kara.moe",
    "sids": [
      "658e2c11-22ee-4f44-98d1-60735e156020"
    ],
    "tags": {
      "authors": [
        "1df04771-a378-4f14-a5e1-1455187d681a"
      ],
      "creators": [
        "dd729cab-2a78-4282-a402-b242e927a0a5"
      ],
      "families": [
        "0377db02-3af6-43b8-9b08-c759df3d25c3"
      ],
      "groups": [
        "24db50aa-a126-4d34-a48a-e45db79c4245"
      ],
      "langs": [
        "b39ffaee-d9cd-44b0-bf35-b019327c3336"
      ],
      "misc": [
        "fe819ff1-9db8-4a0f-85dc-0e322c9126c4"
      ],
      "origins": [
        "938de218-5343-4865-94d3-fb33f2eaa152"
      ],
      "songtypes": [
        "f02ad9b3-0bd9-4aad-85b3-9976739ba0e4"
      ],
      "songwriters": [
        "f7cacb7e-2325-4572-8d4e-53660475eea5",
        "359a599f-4cf4-4f7b-9cc0-3e01b1d4023c"
      ]
    },
    "title": "Die Macht des Zaubersteins",
    "year": 1996
  }
}