{
  "header": {
    "version": 4,
    "description": "Karaoke Mugen Karaoke Data File"
  },
  "medias": [
    {
      "version": "Default",
      "filename": "JPN - Choujinki Metalder - OP - Kimi no Seishun wa Kagayaite Iruka.mp4",
      "audiogain": 6.2,
      "filesize": 17695050,
      "duration": 84,
      "default": true,
      "lyrics": [
        {
          "filename": "JPN - Choujinki Metalder - OP - Kimi no Seishun wa Kagayaite Iruka.ass",
          "default": true,
          "version": "Default"
        }
      ]
    }
  ],
  "data": {
    "authors": [
      "Eden"
    ],
    "created_at": "Wed Oct 11 2017 19:02:23 GMT+0200 (GMT+02:00)",
    "creators": [
      "Toei Company"
    ],
    "groups": [
      "80s"
    ],
    "kid": "cc7452ad-6e0f-45cf-ad41-094e477eb608",
    "langs": [
      "jpn"
    ],
    "modified_at": "Fri Nov 09 2018 22:25:57 GMT+0100 (GMT+01:00)",
    "repository": "kara.moe",
    "title": "Kimi no Seishun wa Kagayaite Iruka",
    "sids": [
      "62eb7341-7a1c-4075-8a4d-1e64f67a9692"
    ],
    "singers": [
      "Isao Sasaki"
    ],
    "songorder": null,
    "songtype": "OP",
    "songwriters": [
      "James Miki",
      "Takashi Miki"
    ],
    "tags": [
      "TAG_REAL",
      "TAG_TOKU",
      "TAG_TVSHOW"
    ],
    "year": 1987
  }
}