{
  "header": {
    "version": 4,
    "description": "Karaoke Mugen Karaoke Data File"
  },
  "medias": [
    {
      "default": true,
      "duration": 91,
      "filename": "JPN - Bokusatsu Tenshi Dokuro-chan 2 - OVA ED - Bokusatsu Ondo de Dokuro-chan.mp4",
      "filesize": 12032679,
      "loudnorm": "-19.44,-7.79,2.30,-29.55,-0.05",
      "lyrics": [
        {
          "default": true,
          "filename": "JPN - Bokusatsu Tenshi Dokuro-chan 2 - OVA ED - Bokusatsu Ondo de Dokuro-chan.ass",
          "version": "Default"
        }
      ],
      "version": "Default"
    }
  ],
  "data": {
    "created_at": "2017-10-11T17:01:47.000Z",
    "kid": "69e61b10-52e9-42ed-904a-25db598fa45c",
    "modified_at": "2021-02-25T10:56:09.184Z",
    "repository": "kara.moe",
    "songname": "JPN - Bokusatsu Tenshi Dokuro-chan 2 - OVA ED - Bokusatsu Ondo de Dokuro-chan",
    "tags": {
      "authors": [
        "a5dbab74-510b-48c5-9cea-5a537a81c974"
      ],
      "collections": [
        "c7db86a0-ff64-4044-9be4-66dd1ef1d1c1"
      ],
      "creators": [
        "00177209-7df7-4d4d-bbcb-4c52d50710d8"
      ],
      "families": [
        "0377db02-3af6-43b8-9b08-c759df3d25c3"
      ],
      "groups": [
        "3c14c864-533c-49e6-a3cc-6969f1233775",
        "8c22c899-b3ed-42da-a548-ce00f950798b"
      ],
      "langs": [
        "4dcf9614-7914-42aa-99f4-dbce2e059133"
      ],
      "origins": [
        "2a6ef087-a000-4f8e-aeb5-9a7968756a36"
      ],
      "series": [
        "420f5396-f66a-487a-8e08-1c1ded7d7a54"
      ],
      "singers": [
        "ce683820-14c3-4fef-a3c1-0eabc0751843"
      ],
      "songtypes": [
        "38c77c56-2b95-4040-b676-0994a8cb0597"
      ],
      "songwriters": [
        "9eb2776f-a305-45e5-91f0-0837de16c987",
        "a2b56a34-833d-4cd0-b587-d8f3032099a8"
      ],
      "franchises": [
        "bd25a525-2a15-4b58-96d9-696d508b087e"
      ]
    },
    "titles": {
      "qro": "Bokusatsu Ondo de Dokuro-chan",
      "jpn": "撲殺音頭でドクロちゃん"
    },
    "titles_default_language": "qro",
    "year": 2007
  }
}