{
  "header": {
    "version": 4,
    "description": "Karaoke Mugen Karaoke Data File"
  },
  "medias": [
    {
      "version": "Default",
      "filename": "JPN - Gintama - SPECIAL OP - Dondake! Gintaman.avi",
      "audiogain": -0.34,
      "filesize": 26844694,
      "duration": 66,
      "default": true,
      "lyrics": [
        {
          "filename": "JPN - Gintama - SPECIAL OP - Dondake! Gintaman.ass",
          "default": true,
          "version": "Default",
          "subchecksum": "8c5afb58481d62ef0f9982ec0acd3686"
        }
      ]
    }
  ],
  "data": {
    "created_at": "2017-10-11T17:01:40.000Z",
    "kid": "7b933f16-bbe2-4781-bf7e-e2fcecfccb92",
    "modified_at": "2019-06-19T15:36:06.000Z",
    "repository": "kara.moe",
    "sids": [
      "0433ab0b-74bb-4837-8f1b-fd17a9e0c526"
    ],
    "tags": {
      "authors": [
        "5bdaba57-27f8-4568-8806-76a807728766"
      ],
      "creators": [
        "ef8f80e1-d244-4aea-b7f0-984d6dd4b82b"
      ],
      "families": [
        "0377db02-3af6-43b8-9b08-c759df3d25c3"
      ],
      "genres": [
        "a0aeef4a-6428-45ff-a6e1-468b595930c2"
      ],
      "groups": [
        "3c14c864-533c-49e6-a3cc-6969f1233775"
      ],
      "langs": [
        "4dcf9614-7914-42aa-99f4-dbce2e059133"
      ],
      "origins": [
        "65f74288-49a5-47b0-82f5-8cd84d1e3dc0",
        "938de218-5343-4865-94d3-fb33f2eaa152"
      ],
      "singers": [
        "016f15c2-4481-4d2f-97fc-72077b2f4a23"
      ],
      "songtypes": [
        "f02ad9b3-0bd9-4aad-85b3-9976739ba0e4"
      ],
      "songwriters": [
        "48f38154-2803-4357-b9f5-e9134bfa1cec"
      ]
    },
    "title": "Dondake! Gintaman",
    "year": 2006
  }
}