{
  "header": {
    "version": 4,
    "description": "Karaoke Mugen Karaoke Data File"
  },
  "medias": [
    {
      "version": "Default",
      "filename": "JPN - Paradise Kiss - OP - Lonely in Gorgeous.mp4",
      "audiogain": -1.09,
      "filesize": 33835107,
      "duration": 92,
      "default": true,
      "lyrics": [
        {
          "filename": "JPN - Paradise Kiss - OP - Lonely in Gorgeous.ass",
          "default": true,
          "version": "Default"
        }
      ]
    }
  ],
  "data": {
    "authors": [
      "Epitanime"
    ],
    "created_at": "Wed Oct 11 2017 19:02:04 GMT+0200 (GMT+02:00)",
    "creators": [
      "MADHOUSE"
    ],
    "groups": [
      "2000s",
      "noitaminA"
    ],
    "kid": "7c4e51bf-4682-485d-b457-fdb4cde0b7f9",
    "langs": [
      "jpn"
    ],
    "modified_at": "Mon Mar 11 2019 20:22:04 GMT+0100 (GMT+01:00)",
    "repository": "kara.moe",
    "title": "♥Lonely in Gorgeous♥",
    "sids": [
      "338c7099-a60f-4be2-baae-cf9eeeba9114"
    ],
    "singers": [
      "Tommy february6"
    ],
    "songorder": null,
    "songtype": "OP",
    "songwriters": [
      "Malibu Convertible"
    ],
    "tags": [
      "TAG_ANIME",
      "TAG_TVSHOW"
    ],
    "year": 2005
  }
}