{
  "header": {
    "version": 4,
    "description": "Karaoke Mugen Karaoke Data File"
  },
  "medias": [
    {
      "version": "Animetal.",
      "filename": "JPN - Mirai Robo Daltanias - SPECIAL AMV - Daltanias no Uta ~ Animetal Vers.mp4",
      "audiogain": -10.07,
      "filesize": 13655537,
      "duration": 70,
      "default": true,
      "lyrics": [
        {
          "filename": "JPN - Mirai Robo Daltanias - SPECIAL AMV - Daltanias no Uta ~ Animetal Vers.ass",
          "default": true,
          "version": "Default",
          "subchecksum": "8f206f25eb91e98fcee66274e322e1f3"
        }
      ]
    }
  ],
  "data": {
    "authors": [
      "Eden"
    ],
    "created_at": "Wed Oct 11 2017 17:01:11 GMT+0200 (GMT+02:00)",
    "creators": [
      "SUNRISE",
      "Toei Animation"
    ],
    "groups": [
      "70s"
    ],
    "kid": "e11e51e2-e569-4aa0-b943-8dd503cddc5b",
    "langs": [
      "jpn"
    ],
    "modified_at": "Wed Jun 19 2019 17:36:07 GMT+0200 (GMT+02:00)",
    "repository": "kara.moe",
    "sids": [
      "3235561c-e10d-48e8-a4f8-70d64719cd51"
    ],
    "singers": [
      "Animetal"
    ],
    "songtype": "AMV",
    "songwriters": [
      "Animetal",
      "Asei Kobayashi",
      "Saburô Yatsude"
    ],
    "tags": [
      "TAG_ANIME",
      "TAG_MECHA",
      "TAG_SPECIAL",
      "TAG_TVSHOW"
    ],
    "title": "Daltanias no Uta ~ Animetal Vers.",
    "year": 1979
  }
}