{
  "header": {
    "version": 4,
    "description": "Karaoke Mugen Karaoke Data File"
  },
  "medias": [
    {
      "version": "Default",
      "filename": "JPN - Ayu Mayu Alternative - PC GAME OP - Kakusei Brave Mind.mp4",
      "audiogain": -8.04,
      "filesize": 26201276,
      "duration": 94,
      "default": true,
      "lyrics": [
        {
          "filename": "JPN - Ayu Mayu Alternative - PC GAME OP - Kakusei Brave Mind.ass",
          "default": true,
          "version": "Default",
          "subchecksum": "9b82015cfbb653e1972f2d44981851a8"
        }
      ]
    }
  ],
  "data": {
    "created_at": "2017-10-11T17:02:29.000Z",
    "kid": "5dca997b-d685-4484-a508-8bdc8347a736",
    "modified_at": "2019-01-25T15:19:22.000Z",
    "repository": "kara.moe",
    "sids": [
      "fce33cde-079f-4c4a-9eaf-16182d951129"
    ],
    "tags": {
      "authors": [
        "8c22c899-b3ed-42da-a548-ce00f950798b"
      ],
      "creators": [
        "5e87ca69-52dd-4df4-957a-5a24d5a19c94"
      ],
      "families": [
        "dbedd6b3-d125-4cd8-aa32-c4175e4ca3a3"
      ],
      "genres": [
        "f60ba57d-5ef4-49e0-b93b-d0dcbcff6592"
      ],
      "groups": [
        "3c14c864-533c-49e6-a3cc-6969f1233775"
      ],
      "langs": [
        "4dcf9614-7914-42aa-99f4-dbce2e059133"
      ],
      "origins": [
        "2f96e82c-c61b-4413-817e-e6b247509b95"
      ],
      "platforms": [
        "3c15f758-e1bc-4266-8bb9-3c14112f504a"
      ],
      "singers": [
        "44be46e3-16bf-4de0-b43f-5518c24ec897"
      ],
      "songtypes": [
        "f02ad9b3-0bd9-4aad-85b3-9976739ba0e4"
      ],
      "songwriters": [
        "1498e794-7325-4902-aa0f-aec73bf4af07"
      ]
    },
    "title": "Kakusei Brave Mind",
    "year": 2008
  }
}