{
  "header": {
    "version": 4,
    "description": "Karaoke Mugen Karaoke Data File"
  },
  "medias": [
    {
      "version": "Default",
      "filename": "JPN - Paradox Live THE ANIMATION - ED2 - Every Day Every Night.mp4",
      "loudnorm": "-18.62,-5.44,5.10,-29.01,-1.18",
      "filesize": 27425597,
      "duration": 90,
      "default": true,
      "lyrics": [
        {
          "filename": "JPN - Paradox Live THE ANIMATION - ED2 - Every Day Every Night.ass",
          "default": true,
          "version": "Default"
        }
      ]
    }
  ],
  "data": {
    "created_at": "2023-10-15T07:54:16.153Z",
    "ignoreHooks": false,
    "kid": "5c682443-8e79-4e4b-bd46-b4c136ebd221",
    "modified_at": "2023-10-15T07:56:34.593Z",
    "repository": "kara.moe",
    "songorder": 2,
    "tags": {
      "authors": [
        "ee8628c8-9b7f-415b-bc0d-9b712d5daf8c"
      ],
      "collections": [
        "c7db86a0-ff64-4044-9be4-66dd1ef1d1c1"
      ],
      "creators": [
        "7658875f-1eb3-4c13-b590-08b3d5d67b06"
      ],
      "families": [
        "0377db02-3af6-43b8-9b08-c759df3d25c3"
      ],
      "groups": [
        "8e209ae4-4381-438f-89dc-1b21752027d2"
      ],
      "langs": [
        "4dcf9614-7914-42aa-99f4-dbce2e059133"
      ],
      "misc": [
        "1d6ceadf-a885-47e5-b23b-c07bf668a424",
        "fe819ff1-9db8-4a0f-85dc-0e322c9126c4"
      ],
      "series": [
        "2c3dd356-7123-4dc4-9aee-ff46bd1cba55"
      ],
      "singers": [
        "06e8a716-74ae-4ccc-843f-21a9a8927a36",
        "b43af946-5787-4527-9c8f-5a3a3e5137f1"
      ],
      "singergroups": [
        "02cd84c4-795b-4b31-b94a-5dde6ddc15ac"
      ],
      "songtypes": [
        "38c77c56-2b95-4040-b676-0994a8cb0597"
      ],
      "franchises": [
        "8ada0331-e624-4181-8714-75d0f964b7fd"
      ]
    },
    "titles": {
      "eng": "Every Day Every Night"
    },
    "titles_default_language": "eng",
    "year": 2023
  }
}