{
  "header": {
    "version": 4,
    "description": "Karaoke Mugen Karaoke Data File"
  },
  "medias": [
    {
      "version": "Default",
      "filename": "JPN - Loveless - OP - Tsuki no Curse.mp4",
      "loudnorm": "-19.29,-4.87,5.80,-29.70,-0.91",
      "filesize": 13418347,
      "duration": 90,
      "default": true,
      "lyrics": [
        {
          "filename": "JPN - Loveless - OP - Tsuki no Curse.ass",
          "default": true,
          "version": "Default"
        }
      ]
    }
  ],
  "data": {
    "created_at": "2017-10-11T17:03:15.000Z",
    "ignoreHooks": false,
    "kid": "7aecded7-1e02-4942-bb4d-78bfc9b60b2c",
    "modified_at": "2024-07-12T22:40:20.391Z",
    "repository": "kara.moe",
    "tags": {
      "authors": [
        "5bdaba57-27f8-4568-8806-76a807728766"
      ],
      "collections": [
        "c7db86a0-ff64-4044-9be4-66dd1ef1d1c1"
      ],
      "creators": [
        "802a8ac8-b16f-40a4-944b-99956798c906"
      ],
      "families": [
        "0377db02-3af6-43b8-9b08-c759df3d25c3"
      ],
      "genres": [
        "724d2d80-a531-4579-bdaf-4a0db9a313d9"
      ],
      "groups": [
        "3c14c864-533c-49e6-a3cc-6969f1233775"
      ],
      "langs": [
        "4dcf9614-7914-42aa-99f4-dbce2e059133"
      ],
      "misc": [
        "fe819ff1-9db8-4a0f-85dc-0e322c9126c4"
      ],
      "origins": [
        "938de218-5343-4865-94d3-fb33f2eaa152"
      ],
      "series": [
        "b5d74b14-5405-49e5-b759-5effc1e5ed7a"
      ],
      "singers": [
        "ac8face8-7eb4-41a8-8919-37e509ffebea"
      ],
      "songtypes": [
        "f02ad9b3-0bd9-4aad-85b3-9976739ba0e4"
      ],
      "songwriters": [
        "1f324dc7-f858-415b-bbc1-41fcce3d6ac7"
      ]
    },
    "titles": {
      "jpn": "月の呪縛",
      "qro": "Tsuki no Curse"
    },
    "titles_default_language": "qro",
    "year": 2005
  }
}