{
  "header": {
    "version": 4,
    "description": "Karaoke Mugen Karaoke Data File"
  },
  "medias": [
    {
      "version": "Default",
      "filename": "JPN - Takoyaki Mantman - OP - Takoyaki Mantoman Shudaika.mp4",
      "audiogain": -3.1,
      "filesize": 9898716,
      "duration": 99,
      "default": true,
      "lyrics": [
        {
          "filename": "JPN - Takoyaki Mantman - OP - Takoyaki Mantoman Shudaika.ass",
          "default": true,
          "version": "Default",
          "subchecksum": "8d1b622e011a79c642acf30ed01fb21f"
        }
      ]
    }
  ],
  "data": {
    "authors": [
      "Ni-jibakurei"
    ],
    "created_at": "Thu May 09 2019 02:35:29 GMT+0200 (GMT+02:00)",
    "creators": [
      "PIERROT"
    ],
    "groups": [
      "90s"
    ],
    "kid": "72f213cd-a5e9-4b3d-8bbf-59db5a32d66a",
    "langs": [
      "jpn"
    ],
    "modified_at": "Wed Jun 19 2019 17:36:09 GMT+0200 (GMT+02:00)",
    "repository": "kara.moe",
    "sids": [
      "9ff62b5f-b12c-40ab-a4af-c491cf8d8b90"
    ],
    "singers": [
      "Isako Saneyoshi"
    ],
    "songtype": "OP",
    "songwriters": [
      "Hiroo Takada",
      "Yasuo Kosugi"
    ],
    "tags": [
      "TAG_ANIME",
      "TAG_TVSHOW"
    ],
    "title": "Takoyaki Mantoman Shudaika",
    "year": 1998
  }
}