{
  "header": {
    "version": 4,
    "description": "Karaoke Mugen Karaoke Data File"
  },
  "medias": [
    {
      "version": "Default",
      "filename": "JPN - A.I.C.O. Incarnation - ONA ED - Michi no Kanata.mp4",
      "audiogain": 7.51,
      "filesize": 30218120,
      "duration": 90,
      "default": true,
      "lyrics": [
        {
          "filename": "JPN - A.I.C.O. Incarnation - ONA ED - Michi no Kanata.ass",
          "default": true,
          "version": "Default"
        }
      ]
    }
  ],
  "data": {
    "authors": [
      "Nock"
    ],
    "created_at": "Tue May 01 2018 17:52:42 GMT+0200 (GMT+02:00)",
    "creators": [
      "bones"
    ],
    "groups": [
      "2010s"
    ],
    "kid": "76bea8b5-200b-4deb-8fe0-2d7b5f1d354a",
    "langs": [
      "jpn"
    ],
    "modified_at": "Tue May 01 2018 17:53:13 GMT+0200 (GMT+02:00)",
    "repository": "kara.moe",
    "title": "Michi no Kanata",
    "sids": [
      "6fc393e4-4ee0-4a6c-9e10-09c04b66c890"
    ],
    "singers": [
      "Haruka Shiraishi"
    ],
    "songorder": null,
    "songtype": "ED",
    "songwriters": [
      "Tarô Iwashiro",
      "Yuriko Mori"
    ],
    "tags": [
      "TAG_ANIME",
      "TAG_ONA"
    ],
    "year": 2018
  }
}