{
  "header": {
    "version": 4,
    "description": "Karaoke Mugen Karaoke Data File"
  },
  "medias": [
    {
      "version": "Default",
      "filename": "JPN - Uchuu Kara no Message Ginga Taisen - OP - Yuusha yo Ginga o Watare.avi",
      "audiogain": 3.9,
      "filesize": 26167136,
      "duration": 79,
      "default": true,
      "lyrics": [
        {
          "filename": "JPN - Uchuu Kara no Message Ginga Taisen - OP - Yuusha yo Ginga o Watare.ass",
          "default": true,
          "version": "Default"
        }
      ]
    }
  ],
  "data": {
    "authors": [
      "Eden"
    ],
    "created_at": "Wed Oct 11 2017 19:01:44 GMT+0200 (GMT+02:00)",
    "creators": [
      "Toei Company"
    ],
    "groups": [
      "70s"
    ],
    "kid": "0935ed6d-a6bc-4a65-a782-bc6e5ad02e02",
    "langs": [
      "jpn"
    ],
    "modified_at": "Mon Mar 26 2018 10:02:30 GMT+0200 (GMT+02:00)",
    "repository": "kara.moe",
    "title": "Yuusha yo Ginga o Watare",
    "sids": [
      "7a7bc519-47a0-4ce0-9e34-710829d9ba19"
    ],
    "singers": [
      "Columbia Dansei Gasshôdan",
      "Isao Sasaki"
    ],
    "songtype": "OP",
    "songwriters": [
      "Shunsuke Kikuchi",
      "Shôtarô Ishinomori"
    ],
    "tags": [
      "TAG_TOKU",
      "TAG_TVSHOW"
    ],
    "year": 1979
  }
}