{
  "header": {
    "version": 4,
    "description": "Karaoke Mugen Karaoke Data File"
  },
  "medias": [
    {
      "version": "Default",
      "filename": "JPN - Naruto Shippuuden - OP17 - Kaze.mp4",
      "audiogain": -5.12,
      "filesize": 35675164,
      "duration": 91,
      "default": true,
      "lyrics": [
        {
          "filename": "JPN - Naruto Shippuuden - OP17 - Kaze.ass",
          "default": true,
          "version": "Default",
          "subchecksum": "5fea1c93e0f23ec968762da24fd5e9e5"
        }
      ]
    }
  ],
  "data": {
    "authors": [
      "Karaoke Mugen"
    ],
    "created_at": "Wed Oct 11 2017 19:02:11 GMT+0200 (GMT+02:00)",
    "creators": [
      "PIERROT"
    ],
    "groups": [
      "2000s"
    ],
    "kid": "c63e2109-f3b0-43d7-8fab-58abc4246cca",
    "langs": [
      "jpn"
    ],
    "modified_at": "Wed Jun 19 2019 17:36:07 GMT+0200 (GMT+02:00)",
    "repository": "kara.moe",
    "sids": [
      "afd38f79-188d-47e4-95c6-f74c38895574"
    ],
    "singers": [
      "Yamazaru"
    ],
    "songorder": 17,
    "songtype": "OP",
    "songwriters": [
      "L!TH!UM",
      "Yamazaru"
    ],
    "tags": [
      "TAG_ANIME",
      "TAG_SHOUNEN",
      "TAG_TVSHOW"
    ],
    "title": "Kaze",
    "year": 2007
  }
}