{
  "header": {
    "version": 4,
    "description": "Karaoke Mugen Karaoke Data File"
  },
  "medias": [
    {
      "version": "Default",
      "filename": "JPN - Makai Tenshi Djibril 4 - GAME OP - the first the last.mp4",
      "audiogain": -6.95,
      "filesize": 34745328,
      "duration": 104,
      "default": true,
      "lyrics": [
        {
          "filename": "JPN - Makai Tenshi Djibril 4 - GAME OP - the first the last.ass",
          "default": true,
          "version": "Default",
          "subchecksum": "480f991746996d60392bcd0a1b056317"
        }
      ]
    }
  ],
  "data": {
    "authors": [
      "Bakaclub"
    ],
    "created_at": "Wed Oct 11 2017 19:00:54 GMT+0200 (GMT+02:00)",
    "creators": [
      "Front Wing"
    ],
    "groups": [
      "2010s"
    ],
    "kid": "90089a26-19b9-461a-b355-477d5a2bd101",
    "langs": [
      "jpn"
    ],
    "modified_at": "Wed Jun 19 2019 17:36:07 GMT+0200 (GMT+02:00)",
    "repository": "kara.moe",
    "sids": [
      "6bb6a22c-acaf-4b1f-8190-83f947dcccec"
    ],
    "singers": [
      "U"
    ],
    "songtype": "OP",
    "songwriters": [
      "Yuu"
    ],
    "tags": [
      "TAG_VIDEOGAME",
      "TAG_VN"
    ],
    "title": "the first the last",
    "year": 2010
  }
}