{
  "header": {
    "version": 4,
    "description": "Karaoke Mugen Karaoke Data File"
  },
  "medias": [
    {
      "version": "Default",
      "filename": "JPN - Satsuriku no Tenshi - OP - Vital.mp4",
      "audiogain": -0.66,
      "filesize": 17634539,
      "duration": 89,
      "default": true,
      "lyrics": [
        {
          "filename": "JPN - Satsuriku no Tenshi - OP - Vital.ass",
          "default": true,
          "version": "Default"
        }
      ]
    }
  ],
  "data": {
    "authors": [
      "KuroSensei"
    ],
    "created_at": "Tue Oct 02 2018 12:16:58 GMT+0200 (GMT+02:00)",
    "creators": [
      "J.C.STAFF"
    ],
    "groups": [
      "2010s"
    ],
    "kid": "9bcf7240-cc65-438d-beaf-fd614a132577",
    "langs": [
      "jpn"
    ],
    "modified_at": "Wed Nov 14 2018 22:34:06 GMT+0100 (GMT+01:00)",
    "repository": "kara.moe",
    "title": "Vital",
    "sids": [
      "b997f81b-7417-4e21-9e88-d9e17227e18e"
    ],
    "singers": [
      "Masaaki Endô"
    ],
    "songorder": null,
    "songtype": "OP",
    "songwriters": [
      "Jin"
    ],
    "tags": [
      "TAG_ANIME",
      "TAG_TVSHOW"
    ],
    "year": 2018
  }
}