{
  "header": {
    "version": 4,
    "description": "Karaoke Mugen Karaoke Data File"
  },
  "medias": [
    {
      "version": "Default",
      "filename": "JPN - Mahoromatic Automatic Maiden - OP - Kaerimichi.mp4",
      "audiogain": 5.62,
      "filesize": 47729461,
      "duration": 92,
      "default": true,
      "lyrics": [
        {
          "filename": "JPN - Mahoromatic Automatic Maiden - OP - Kaerimichi.ass",
          "default": true,
          "version": "Default"
        }
      ]
    }
  ],
  "data": {
    "authors": [
      "Epitanime"
    ],
    "created_at": "Wed Oct 11 2017 19:02:18 GMT+0200 (GMT+02:00)",
    "creators": [
      "GAINAX",
      "SHAFT"
    ],
    "groups": [
      "2000s"
    ],
    "kid": "5d1c09b3-e21c-4bf3-8a2a-1335ceadc873",
    "langs": [
      "jpn"
    ],
    "modified_at": "Mon Mar 26 2018 10:02:29 GMT+0200 (GMT+02:00)",
    "repository": "kara.moe",
    "title": "Kaerimichi",
    "sids": [
      "7a54c0fe-0ec2-4596-8923-fa6b92b10f00"
    ],
    "singers": [
      "Ayako Kawasumi"
    ],
    "songtype": "OP",
    "songwriters": [
      "Kiyomi Kumano",
      "Toshio Masuda"
    ],
    "tags": [
      "TAG_ANIME",
      "TAG_TVSHOW"
    ],
    "year": 2001
  }
}