{
  "header": {
    "version": 4,
    "description": "Karaoke Mugen Karaoke Data File"
  },
  "medias": [
    {
      "version": "Default",
      "filename": "JPN - Princess Connect! Re Dive - GAME ED4 - Egao no My Home.mp4",
      "audiogain": 0.32,
      "loudnorm": "-18.58,-5.02,5.30,-29.26,-1.01",
      "filesize": 18410813,
      "duration": 80,
      "default": true,
      "lyrics": [
        {
          "filename": "JPN - Princess Connect! Re Dive - GAME ED4 - Egao no My Home.ass",
          "default": true,
          "version": "Default"
        }
      ]
    }
  ],
  "data": {
    "created_at": "2022-03-24T20:28:48.022Z",
    "ignoreHooks": false,
    "kid": "407143dd-8569-4c53-9fd9-610a3ec1074a",
    "modified_at": "2022-03-24T20:29:33.074Z",
    "repository": "kara.moe",
    "songorder": 4,
    "tags": {
      "authors": [
        "06852e02-b77e-4106-b6f7-2d03942ad0ea"
      ],
      "collections": [
        "c7db86a0-ff64-4044-9be4-66dd1ef1d1c1"
      ],
      "creators": [
        "344cb973-3dac-4bac-b6b0-71243417856b"
      ],
      "genres": [
        "4b80eca6-f44f-4262-a8d0-b6879d6b70cb"
      ],
      "groups": [
        "ae613721-1fbe-480d-ba6b-d6d0702b184d"
      ],
      "langs": [
        "4dcf9614-7914-42aa-99f4-dbce2e059133"
      ],
      "misc": [
        "1d6ceadf-a885-47e5-b23b-c07bf668a424",
        "fe819ff1-9db8-4a0f-85dc-0e322c9126c4"
      ],
      "platforms": [
        "213a1a15-e73a-4a08-b3f6-b6e2745a82e5"
      ],
      "series": [
        "ab7828d2-8048-4392-bd92-4c8aed8d6089"
      ],
      "singers": [
        "0abac712-6493-4c55-856b-e88f2687e34b",
        "a6042b25-be94-49bf-ab1b-1ba48a565df3"
      ],
      "songtypes": [
        "38c77c56-2b95-4040-b676-0994a8cb0597"
      ],
      "songwriters": [
        "30176855-4b20-4c9f-965c-3f7cf86c20d5",
        "d09eb571-76bb-4ef3-a7e9-4cf27229b88c"
      ],
      "franchises": [
        "fff43282-57cd-491e-b92f-541b42365241"
      ],
      "origins": [
        "dbedd6b3-d125-4cd8-aa32-c4175e4ca3a3"
      ]
    },
    "titles": {
      "qro": "Egao no My Home",
      "jpn": "えがおのマイホーム"
    },
    "titles_default_language": "qro",
    "title": "Egao no My Home",
    "year": 2018
  }
}