{
  "header": {
    "version": 4,
    "description": "Karaoke Mugen Karaoke Data File"
  },
  "medias": [
    {
      "version": "Default",
      "filename": "JPN - Onegai Teacher - MV - Snow Angel.mp4",
      "audiogain": 3.06,
      "filesize": 54888750,
      "duration": 266,
      "default": true,
      "lyrics": [
        {
          "filename": "JPN - Onegai Teacher - MV - Snow Angel.ass",
          "default": true,
          "version": "Default",
          "subchecksum": "614146bb339ac5e74fef534a449fe02d"
        }
      ]
    }
  ],
  "data": {
    "authors": [
      "Karaoke Mugen"
    ],
    "created_at": "Wed Oct 11 2017 19:01:44 GMT+0200 (GMT+02:00)",
    "creators": [
      "Daume"
    ],
    "groups": [
      "2000s"
    ],
    "kid": "2b65ad78-702f-496e-852f-ee184dba5f3b",
    "langs": [
      "jpn"
    ],
    "modified_at": "Wed Jun 19 2019 17:36:08 GMT+0200 (GMT+02:00)",
    "repository": "kara.moe",
    "sids": [
      "9f12ae5a-4a54-457d-86d6-b14e516b5c36"
    ],
    "singers": [
      "KOTOKO"
    ],
    "songtype": "MV",
    "songwriters": [
      "KOTOKO",
      "Kazuya Takase"
    ],
    "tags": [
      "TAG_ANIME",
      "TAG_CREDITLESS",
      "TAG_LONG",
      "TAG_TVSHOW"
    ],
    "title": "Snow Angel",
    "year": 2002
  }
}