{
  "header": {
    "version": 4,
    "description": "Karaoke Mugen Karaoke Data File"
  },
  "medias": [
    {
      "version": "Default",
      "filename": "JPN - Chikyuu Shoujo Arjuna - ED2 - Sanctuary.mp4",
      "audiogain": -0.87,
      "filesize": 6187895,
      "duration": 100,
      "default": true,
      "lyrics": [
        {
          "filename": "JPN - Chikyuu Shoujo Arjuna - ED2 - Sanctuary.ass",
          "default": true,
          "version": "Default",
          "subchecksum": "b70805f01499e98c72160a9cd7c37751"
        }
      ]
    }
  ],
  "data": {
    "created_at": "2020-02-04T20:48:23.302Z",
    "kid": "eae0ecd1-a130-46ee-b873-154b9cc6a5be",
    "modified_at": "2020-02-04T20:52:38.429Z",
    "repository": "kara.moe",
    "sids": [
      "5b2648fa-82b6-4eff-954a-4df48b41cb8e"
    ],
    "songorder": 2,
    "tags": {
      "authors": [
        "deacc981-4b8a-4c24-a016-0000c6aa4d7d"
      ],
      "creators": [
        "0041fabf-4b82-4ecd-961b-e4c49b8c88be"
      ],
      "families": [
        "0377db02-3af6-43b8-9b08-c759df3d25c3"
      ],
      "groups": [
        "3c14c864-533c-49e6-a3cc-6969f1233775"
      ],
      "langs": [
        "4dcf9614-7914-42aa-99f4-dbce2e059133"
      ],
      "origins": [
        "938de218-5343-4865-94d3-fb33f2eaa152"
      ],
      "singers": [
        "1e93160f-11bb-4d02-b716-4660cb29206e"
      ],
      "songtypes": [
        "38c77c56-2b95-4040-b676-0994a8cb0597"
      ],
      "songwriters": [
        "af0be06d-ea2d-4f46-85d1-58cf9f42532a"
      ]
    },
    "title": "Sanctuary",
    "year": 2001
  }
}