{
  "header": {
    "version": 4,
    "description": "Karaoke Mugen Karaoke Data File"
  },
  "medias": [
    {
      "version": "Default",
      "filename": "JPN - Knight's & Magic - OP - Hello! My World!!.mp4",
      "audiogain": -7.5,
      "filesize": 55461661,
      "duration": 92,
      "default": true,
      "lyrics": [
        {
          "filename": "JPN - Knight's & Magic - OP - Hello! My World!!.ass",
          "default": true,
          "version": "Default"
        }
      ]
    }
  ],
  "data": {
    "authors": [
      "KuroSensei"
    ],
    "created_at": "Thu Jul 26 2018 21:47:32 GMT+0200 (GMT+02:00)",
    "creators": [
      "8bit"
    ],
    "groups": [
      "2010s",
      "Isekai"
    ],
    "kid": "74251545-db43-4a82-9264-bf6c7a2cdaca",
    "langs": [
      "jpn"
    ],
    "modified_at": "Sat Dec 08 2018 16:07:45 GMT+0100 (GMT+01:00)",
    "repository": "kara.moe",
    "title": "Hello! My World!!",
    "sids": [
      "20fe07c9-89b3-474d-a9e3-ad86b121f172"
    ],
    "singers": [
      "fhána"
    ],
    "songtype": "OP",
    "songwriters": [
      "Hideki Hayashi",
      "Jun'ichi Satô"
    ],
    "tags": [
      "TAG_ANIME",
      "TAG_TVSHOW"
    ],
    "year": 2017
  }
}