{
  "header": {
    "version": 4,
    "description": "Karaoke Mugen Karaoke Data File"
  },
  "medias": [
    {
      "version": "Default",
      "filename": "JPN - Touken Ranbu Hanamaru - ED5 - Izuru Tsuki Shouen no Uta.mp4",
      "audiogain": 1.08,
      "filesize": 46756354,
      "duration": 92,
      "default": true,
      "lyrics": [
        {
          "filename": "JPN - Touken Ranbu Hanamaru - ED5 - Izuru Tsuki Shouen no Uta.ass",
          "default": true,
          "version": "Default"
        }
      ]
    }
  ],
  "data": {
    "authors": [
      "Nabashi"
    ],
    "created_at": "Sat Jun 16 2018 01:12:17 GMT+0200 (GMT+02:00)",
    "creators": [
      "Doga Kobo"
    ],
    "groups": [
      "2010s"
    ],
    "kid": "4175adf8-39ce-49a9-aa97-de4618381a20",
    "langs": [
      "jpn"
    ],
    "modified_at": "Thu Dec 06 2018 00:07:36 GMT+0100 (GMT+01:00)",
    "repository": "kara.moe",
    "title": "Izuru Tsuki Shôen no Uta",
    "sids": [
      "387472c1-ec8a-41c4-9e5a-29c836768b10"
    ],
    "singers": [
      "Kaito Ishikawa",
      "Kôsuke Toriumi",
      "Sôma Saitô",
      "Takuya Satô"
    ],
    "songorder": 5,
    "songtype": "ED",
    "songwriters": [
      "Genki Mizuno",
      "Kensuke Inage"
    ],
    "tags": [
      "TAG_ANIME",
      "TAG_TVSHOW"
    ],
    "year": 2016
  }
}