{
  "header": {
    "version": 4,
    "description": "Karaoke Mugen Karaoke Data File"
  },
  "medias": [
    {
      "version": "Default",
      "filename": "JPN - Seikai Suru Kado - OP - Tabiuta.mp4",
      "loudnorm": "-22.66,-12.31,4.80,-32.77,-1.27",
      "filesize": 36873536,
      "duration": 92,
      "default": true,
      "lyrics": [
        {
          "filename": "JPN - Seikai Suru Kado - OP - Tabiuta.ass",
          "default": true,
          "version": "Default"
        }
      ]
    }
  ],
  "data": {
    "created_at": "2018-04-20T19:27:30.000Z",
    "ignoreHooks": false,
    "kid": "83b9078e-62de-40d8-a3c3-e884b1148667",
    "modified_at": "2024-11-18T15:55:51.888Z",
    "repository": "kara.moe",
    "tags": {
      "authors": [
        "2a9bbf75-0722-4b4a-9935-caa92f38fdd1"
      ],
      "collections": [
        "c7db86a0-ff64-4044-9be4-66dd1ef1d1c1"
      ],
      "creators": [
        "f694bf43-b427-4244-9744-9d3f84fd8a31"
      ],
      "families": [
        "0377db02-3af6-43b8-9b08-c759df3d25c3"
      ],
      "groups": [
        "ae613721-1fbe-480d-ba6b-d6d0702b184d"
      ],
      "langs": [
        "4dcf9614-7914-42aa-99f4-dbce2e059133"
      ],
      "origins": [
        "938de218-5343-4865-94d3-fb33f2eaa152"
      ],
      "series": [
        "45915df9-fbce-46fe-850f-fd92c4815016"
      ],
      "singers": [
        "dfddf0a7-15e4-4fa7-90e7-fead611ee6c7"
      ],
      "songtypes": [
        "f02ad9b3-0bd9-4aad-85b3-9976739ba0e4"
      ],
      "songwriters": [
        "25792642-7da1-4014-aa17-c0365b2d49fd",
        "432cd4fc-5504-4e7a-9114-6a607b2af4ad"
      ]
    },
    "titles": {
      "jpn": "旅詩",
      "qro": "Tabiuta"
    },
    "titles_default_language": "qro",
    "year": 2017
  }
}