{
  "header": {
    "version": 4,
    "description": "Karaoke Mugen Karaoke Data File"
  },
  "medias": [
    {
      "version": "Default",
      "filename": "JPN - Cross Ange Tenshi to Ryuu no Rondo - AMV - Towagatari ~El Ragna~.mp4",
      "audiogain": -7.95,
      "filesize": 133382962,
      "duration": 261,
      "default": true,
      "lyrics": [
        {
          "filename": "JPN - Cross Ange Tenshi to Ryuu no Rondo - AMV - Towagatari ~El Ragna~.ass",
          "default": true,
          "version": "Default",
          "subchecksum": "df6a53015066c72883fa0892e4e6d14d"
        }
      ]
    }
  ],
  "data": {
    "created_at": "2019-06-16T20:38:19.000Z",
    "kid": "9616cb53-3ccb-4fd8-be67-aa2e7b17a8cb",
    "modified_at": "2019-06-19T15:36:05.000Z",
    "repository": "kara.moe",
    "sids": [
      "10730638-b625-4aa1-811c-687d080cda8e"
    ],
    "tags": {
      "authors": [
        "523ead5e-981e-4993-af29-12524f7edcf1"
      ],
      "creators": [
        "ef8f80e1-d244-4aea-b7f0-984d6dd4b82b"
      ],
      "families": [
        "0377db02-3af6-43b8-9b08-c759df3d25c3"
      ],
      "groups": [
        "ae613721-1fbe-480d-ba6b-d6d0702b184d"
      ],
      "langs": [
        "4dcf9614-7914-42aa-99f4-dbce2e059133"
      ],
      "origins": [
        "938de218-5343-4865-94d3-fb33f2eaa152"
      ],
      "series": [
        "10730638-b625-4aa1-811c-687d080cda8e"
      ],
      "singers": [
        "6d2045b2-80ab-45ff-a131-c4df02ef52d1",
        "a6042b25-be94-49bf-ab1b-1ba48a565df3"
      ],
      "songtypes": [
        "a6c79ce5-89ee-4d50-afe8-3abd7317f6c2"
      ],
      "songwriters": [
        "cc413549-14dd-4cc1-87d6-022fa80fbdd8"
      ]
    },
    "title": "Towagatari ~El Ragna~",
    "year": 2014
  }
}