{
  "header": {
    "description": "Karaoke Mugen Tag File",
    "version": 1
  },
  "tag": {
    "external_database_ids": {
      "anilist": 100532,
      "myanimelist": 36800,
      "kitsu": 14015
    },
    "i18n": {
      "eng": "Amanchu! Advance",
      "jpn": "あまんちゅ! ~あどばんす~",
      "kor": "아만츄! 어드밴스",
      "qro": "Amanchu! Advance"
    },
    "modified_at": "2020-03-31T19:04:30.938Z",
    "name": "Amanchu! Advance",
    "repository": "kara.moe",
    "tid": "0f6a3949-8d75-4f06-9751-e9e197e84a15",
    "types": [
      "1",
      "series"
    ]
  }
}