{
  "header": {
    "description": "Karaoke Mugen Tag File",
    "version": 1
  },
  "tag": {
    "aliases": [
      "Binan Koukou Chikyuu Bouei Bu LOVE!",
      "Binan Koukou Chikyuu Bouei-bu Love!",
      "Binan Koukou Chikyuu Boueibu Love!",
      "koukou",
      "chikyuu",
      "bouei"
    ],
    "i18n": {
      "eng": "Cute High Earth Defense Club Love!",
      "fre": "Binan Kôkô Chikyû Bôei Bu LOVE!",
      "jpn": "美男高校地球防衛部LOVE!",
      "qro": "Binan Kôkô Chikyû Bôei Bu LOVE!"
    },
    "modified_at": "2020-03-31T19:04:31.070Z",
    "name": "Binan Kôkô Chikyû Bôei Bu LOVE!",
    "repository": "kara.moe",
    "tid": "970473d9-746a-4487-9566-4c110a979392",
    "types": [
      "18",
      "franchises"
    ]
  }
}