{
  "header": {
    "description": "Karaoke Mugen Tag File",
    "version": 1
  },
  "tag": {
    "aliases": [
      "City Hunter : La Mort de Ryo Saeba",
      "City Hunter: Kinkyuu Namachuukei!? Kyouakuhan Saeba Ryou no Saigo",
      "Nicky Larson : Flash spécial !? La mort de Ryô Saeba",
      "kinkyuu",
      "kyouakuhan",
      "ryou"
    ],
    "external_database_ids": {
      "anilist": 1479,
      "myanimelist": 1479,
      "kitsu": 1325
    },
    "i18n": {
      "eng": "City Hunter: Death of the Vicious Criminal Ryo Saeba",
      "fre": "City Hunter : La Mort de City Hunter",
      "ger": "City Hunter: Ryô Saeba, Live on the Scene",
      "ita": "City Hunter Special 6 - Arrestate Ryo Saeba",
      "jpn": "シティーハンタースペシャル 緊急生中継!?凶悪犯冴羽リョウの最期",
      "qro": "City Hunter Special: Kinkyû Namachuukei!? Kyôakuhan Saeba Ryô no Saigo"
    },
    "modified_at": "2020-05-03T13:12:52.380Z",
    "name": "City Hunter Special: Kinkyû Namachuukei!? Kyôakuhan Saeba Ryô no Saigo",
    "repository": "kara.moe",
    "tid": "67c33fc5-0367-4c77-9bba-cecbf2d10a8d",
    "types": [
      "1",
      "series"
    ]
  }
}