{
  "header": {
    "description": "Karaoke Mugen Tag File",
    "version": 1
  },
  "tag": {
    "aliases": [
      "Furuba",
      "FB",
      "fruba"
    ],
    "external_database_ids": {
      "anilist": 111762,
      "myanimelist": 40417,
      "kitsu": 42554
    },
    "i18n": {
      "eng": "Fruits Basket (2019) 2nd Season",
      "jpn": "フルーツバスケット 2nd season",
      "fre": "Fruits Basket (2019) saison 2",
      "qro": "Fruits Basket (2019) 2nd Season"
    },
    "modified_at": "2021-05-09T10:59:54.000Z",
    "name": "Fruits Basket (2019) 2nd Season",
    "repository": "kara.moe",
    "tid": "c0ee0466-be4b-4dcb-a638-2957ccea2933",
    "types": [
      "1",
      "series"
    ]
  }
}