{
  "header": {
    "description": "Karaoke Mugen Tag File",
    "version": 1
  },
  "tag": {
    "aliases": [
      "Ikikoi",
      "Suddenly i'm falling in love with you",
      "いき恋"
    ],
    "i18n": {
      "eng": "Ikinari Anata ni Koishiteiru",
      "jpn": "いきなりあなたに恋している",
      "qro": "Ikinari Anata ni Koishiteru"
    },
    "modified_at": "2020-03-31T19:04:31.761Z",
    "name": "Ikinari Anata ni Koishiteru",
    "repository": "kara.moe",
    "tid": "acdfd70d-a5c7-42db-92b9-58ea759a437d",
    "types": [
      "1",
      "series"
    ]
  }
}