{
  "header": {
    "description": "Karaoke Mugen Tag File",
    "version": 1
  },
  "tag": {
    "external_database_ids": {
      "anilist": 15315,
      "myanimelist": 15315,
      "kitsu": 7239
    },
    "i18n": {
      "eng": "Problem children are coming from another world, aren't they?",
      "fre": "Mondaiji-tachi ga Isekai kara Kuru Sô Desu yo?",
      "jpn": "問題児たちが異世界から来るそうですよ?",
      "qro": "Mondaiji-tachi ga Isekai Kara Kuru Sou Desu Yo"
    },
    "modified_at": "2020-03-31T19:04:32.267Z",
    "name": "Mondaiji-tachi ga Isekai Kara Kuru Sou Desu Yo",
    "repository": "kara.moe",
    "tid": "48ee1dfa-1d33-4435-910c-6aa8b46c8181",
    "types": [
      "1",
      "series"
    ]
  }
}