{
  "header": {
    "description": "Karaoke Mugen Tag File",
    "version": 1
  },
  "tag": {
    "aliases": [
      "Pkmn",
      "Pocket Monsters BW",
      "Pokémon BW",
      "Pokémon Best Wishes"
    ],
    "external_database_ids": {
      "anilist": 9107,
      "myanimelist": 9107,
      "kitsu": 5605
    },
    "i18n": {
      "eng": "Pokémon: Black & White",
      "fre": "Pokémon : Noir & Blanc",
      "jpn": "ポケットモンスターベストウイッシュ",
      "qro": "Pocket Monsters Best Wishes!"
    },
    "modified_at": "2020-06-21T23:45:31.966Z",
    "name": "Pocket Monsters Best Wishes!",
    "repository": "kara.moe",
    "tid": "d0a95f28-67ba-48d9-8a59-a52570eaaedf",
    "types": [
      "1",
      "series"
    ]
  }
}