{
  "header": {
    "description": "Karaoke Mugen Tag File",
    "version": 1
  },
  "tag": {
    "external_database_ids": {
      "anilist": 103118,
      "myanimelist": 38006,
      "kitsu": 44227
    },
    "i18n": {
      "eng": "League of Nations Air Force Aviation Magic Band Luminous Witches",
      "jpn": "連盟空軍航空魔法音楽隊ルミナスウィッチーズ",
      "qro": "Renmei Kuugun Koukuu Mahou Ongakutai: Luminous Witches"
    },
    "name": "Renmei Kuugun Koukuu Mahou Ongakutai: Luminous Witches",
    "repository": "kara.moe",
    "short": "Luminous Witches",
    "tid": "445c061e-950a-4a05-b695-dc0fde189c34",
    "types": [
      "1",
      "series"
    ]
  }
}