{
  "header": {
    "description": "Karaoke Mugen Tag File",
    "version": 1
  },
  "tag": {
    "external_database_ids": {
      "anilist": 152,
      "kitsu": 130,
      "myanimelist": 152
    },
    "i18n": {
      "eng": "Solty Rei",
      "jpn": "ソルティレイ",
      "qro": "Solty Rei",
      "ara": "الصياد",
      "fre": "Solty Rei",
      "chi": "曙光少女",
      "ger": "Solty Rei"
    },
    "name": "Solty Rei",
    "repository": "kara.moe",
    "tid": "779e8ff7-a937-4af9-9ff1-253108a294d5",
    "types": [
      "1",
      "series"
    ]
  }
}