{
  "header": {
    "description": "Karaoke Mugen Tag File",
    "version": 1
  },
  "tag": {
    "aliases": [
      "Senkei Kôsoku no Phenogram",
      "s;g",
      "sg",
      "シュタインズ・ゲート",
      "steins gate"
    ],
    "i18n": {
      "eng": "Steins;Gate: Linear Bounded Phenogram",
      "jpn": "STEINS;GATE 線形拘束のフェノグラム",
      "qro": "Steins;Gate Senkei Kousoku no Phenogram"
    },
    "modified_at": "2020-03-31T19:04:32.834Z",
    "name": "Steins;Gate Senkei Kousoku no Phenogram",
    "repository": "kara.moe",
    "tid": "1513d47f-b1e0-465b-8679-4cfeb92893fa",
    "types": [
      "1",
      "series"
    ]
  }
}