{
  "header": {
    "description": "Karaoke Mugen Tag File",
    "version": 1
  },
  "tag": {
    "aliases": [
      "Howl at the Moon"
    ],
    "i18n": {
      "eng": "Yozakura Quartet: Tsuki ni Naku",
      "jpn": "夜桜四重奏 ツキニナク",
      "qjr": "Yozakura Quartet: Tsuki ni Naku"
    },
    "modified_at": "2020-12-01T18:17:41.484Z",
    "name": "Yozakura Quartet: Tsuki ni Naku",
    "repository": "kara.moe",
    "tid": "195d5360-90c9-405d-9d9b-81789157408a",
    "types": [
      "series"
    ]
  }
}