{
  "header": {
    "version": 3,
    "description": "Karaoke Mugen Series File"
  },
  "series": {
    "name": "Kôtetsujô no Kabaneri -Ran- Hajimaru Michiato",
    "aliases": [
      "kabaneri",
      "Желязната крепост на мъртвите",
      "Заклеймённые из «Стальной крепости»",
      "Кабанери от Желязната крепост",
      "Koutetsujou no Kabaneri",
      "Kabaneri of the Iron Fortress -Revolt- Beginning Tracks"
    ],
    "i18n": {
      "jpn": "甲鉄城のカバネリ -乱- 始まる軌跡",
      "eng": "Kabaneri of the Iron Fortress ~Revolt~ Beginning Tracks"
    },
    "sid": "66fb3c85-96b7-4cfe-8c0d-dae374757723",
    "repository": "kara.moe"
  }
}