{
  "header": {
    "version": 3,
    "description": "Karaoke Mugen Series File"
  },
  "series": {
    "name": "Trinity Blood",
    "aliases": [
      "Kızıl Kan",
      "T Blood",
      "T-Blood",
      "TB",
      "trinity",
      "ترينيتي بلود",
      "圣魔之血"
    ],
    "i18n": {
      "jpn": "トリニティ・ブラッド",
      "pol": "Trinity Blood",
      "fre": "Trinity Blood",
      "fin": "Trinity Blood",
      "por": "Trinity Blood",
      "eng": "Trinity Blood",
      "ger": "Trinity Blood",
      "rus": "Trinity Blood (Кровь Триединства)",
      "hun": "Vér és kereszt",
      "kor": "트리니티 블러드"
    },
    "sid": "224715c4-5262-4059-8fa9-76963716ac88",
    "repository": "kara.moe"
  }
}